{"created":"2020-04-08T18:36:58.212129","id":"","iteration":"","predictions":[{"boundingBox":{"height":0.29129957,"left":0.65293093,"top":0.03616822,"width":0.29018944},"probability":0.81046504,"tagId":0,"tagName":"MVP"},{"boundingBox":{"height":0.23093931,"left":0.35431859,"top":0.07159848,"width":0.20494867},"probability":0.49723253,"tagId":0,"tagName":"MVP"},{"boundingBox":{"height":0.22276918,"left":0.3527158,"top":0.42022111,"width":0.20117629},"probability":0.36720365,"tagId":0,"tagName":"MVP"},{"boundingBox":{"height":0.19274786,"left":0.14876342,"top":-0.00570262,"width":0.08578076},"probability":0.23912002,"tagId":0,"tagName":"MVP"},{"boundingBox":{"height":0.89381491,"left":-0.02441453,"top":0.01559119,"width":0.33418928},"probability":0.22741263,"tagId":0,"tagName":"MVP"}],"project":""}
