{"created":"2020-05-21T15:53:36.825605","id":"","iteration":"","predictions":[{"boundingBox":{"height":0.22956734,"left":0.31379168,"top":0.08137916,"width":0.19807253},"probability":0.69576764,"tagId":0,"tagName":"MVP"},{"boundingBox":{"height":0.20241674,"left":0.62238935,"top":0.07776334,"width":0.17865608},"probability":0.5265556,"tagId":0,"tagName":"MVP"},{"boundingBox":{"height":0.22069961,"left":0.33410361,"top":0.44395044,"width":0.19296324},"probability":0.27868754,"tagId":0,"tagName":"MVP"},{"boundingBox":{"height":0.73658555,"left":-0.03193925,"top":0.2345195,"width":0.66816614},"probability":0.23114306,"tagId":0,"tagName":"MVP"},{"boundingBox":{"height":0.15169506,"left":0.37061761,"top":0.46736355,"width":0.11535697},"probability":0.19663118,"tagId":0,"tagName":"MVP"},{"boundingBox":{"height":0.70680137,"left":0.20846755,"top":0.18347901,"width":0.73631444},"probability":0.17630386,"tagId":0,"tagName":"MVP"}],"project":""}
